ctransformers/__init__.py
ctransformers/hub.py
ctransformers/langchain.py
ctransformers/lib.py
ctransformers/llm.py
ctransformers/logger.py
ctransformers/transformers.py
ctransformers/utils.py
ctransformers/gptq/__init__.py
ctransformers/gptq/hub.py
ctransformers/gptq/llm.py
ctransformers/lib/avx/ctransformers.dll
ctransformers/lib/avx/libctransformers.dylib
ctransformers/lib/avx/libctransformers.so
ctransformers/lib/avx2/ctransformers.dll
ctransformers/lib/avx2/libctransformers.dylib
ctransformers/lib/avx2/libctransformers.so
ctransformers/lib/basic/ctransformers.dll
ctransformers/lib/basic/libctransformers.dylib
ctransformers/lib/basic/libctransformers.so
ctransformers/lib/cuda/ctransformers.dll
ctransformers/lib/cuda/libctransformers.so
ctransformers-0.2.27.dist-info/LICENSE
ctransformers-0.2.27.dist-info/METADATA
ctransformers-0.2.27.dist-info/WHEEL
ctransformers-0.2.27.dist-info/top_level.txt
ctransformers-0.2.27.dist-info/RECORD
