Metadata-Version: 2.1
Name: ctransformers
Version: 0.2.27
Summary: Python bindings for the Transformer models implemented in C/C++ using GGML library.
Home-page: https://github.com/marella/ctransformers
Author: Ravindra Marella
Author-email: mv.ravindra007@gmail.com
License: MIT
Keywords: ctransformers transformers ai llm
Platform: UNKNOWN
Classifier: Development Status :: 1 - Planning
Classifier: Intended Audience :: Developers
Classifier: Intended Audience :: Education
Classifier: Intended Audience :: Science/Research
Classifier: License :: OSI Approved :: MIT License
Classifier: Programming Language :: Python :: 3
Classifier: Topic :: Scientific/Engineering
Classifier: Topic :: Scientific/Engineering :: Mathematics
Classifier: Topic :: Scientific/Engineering :: Artificial Intelligence
Classifier: Topic :: Software Development
Classifier: Topic :: Software Development :: Libraries
Classifier: Topic :: Software Development :: Libraries :: Python Modules
Provides-Extra: cuda
Provides-Extra: gptq
Provides-Extra: tests
